
[{
		"categoryId": 4,
		"categoryTitle": "SERIE A   ------→",
		"categoryItemList": [
	

		


	
	
			
			{
    "bannerCategoryId": "4",
     "fileUrl": "http://t5gokh6s.megatv.fun/iptv/6GZMB8T2W5QZEU/7349/index.m3u8",
    "id": 2,
    "imageUrl": "https://i.ytimg.com/vi/bgPQWXmb-_c/maxresdefault.jpg",
    "movieName": "Parma vs Roma"
  },
		{
    "bannerCategoryId": "4",
     "fileUrl": "https://www.livedoomovies.com/02_SPORTTV_3_720p/chunklist.m3u8",
    "id": 2,
    "imageUrl": "https://i.ytimg.com/vi/eq-To4AYkk4/maxresdefault.jpg",
    "movieName": "Torino vs Internazionale"
  },
	
			
			{
    "bannerCategoryId": "4",
     "fileUrl": "https://www.livedoomovies.com/02_SPORTTV_3_720p/chunklist.m3u8",
    "id": 2,
    "imageUrl": "https://i.ytimg.com/vi/iCm_-dvbAak/maxresdefault.jpg",
    "movieName": "Cagliari vs Juventus"
  },
{
    "bannerCategoryId": "4",
     "fileUrl": "https://www.livedoomovies.com/02_SPORTTV_3_720p/chunklist.m3u8",
    "id": 2,
    "imageUrl": "https://i.ytimg.com/vi/Dg-v_ApPJGw/maxresdefault.jpg",
    "movieName": "Milan vs Napoli"

  }


		]
	}
 ]
