

[
 
    
	
	
	

	{
	"bannerCategoryId": "1",
		
	"fileUrl": "https://www.livedoomovies.com/02_PremierHD2_480p/chunklist.m3u8",
         "id": 2,
        "imageUrl": "https://i.ytimg.com/vi/A9Wk_ZZgpZE/hqdefault.jpg",
        "movieName": "Wolverhampton Wanderers vs Liverpool"
  },
{
	"bannerCategoryId": "2",
		
	"fileUrl": "https://www.livedoomovies.com/02_PremierHD2_480p/chunklist.m3u8",
         "id": 2,
        "imageUrl": "https://i.ytimg.com/vi/A9Wk_ZZgpZE/hqdefault.jpg",
        "movieName": "Wolverhampton Wanderers vs Liverpool"
  },
  
   
{
	"bannerCategoryId": "3",
	"fileUrl": "http://ott-cdn.ucom.am/s81/04.m3u8",
         "id": 2,
        "imageUrl": "https://i.ytimg.com/vi/2HmfoYhoDuk/maxresdefault.jpg",
        "movieName": "Barcelona vs Huesca"
  },
	

		
	
			
		

{
    "bannerCategoryId": "4",
     "fileUrl": "https://www.livedoomovies.com/02_SPORTTV_3_720p/chunklist.m3u8",
    "id": 2,
    "imageUrl": "https://i.ytimg.com/vi/Dg-v_ApPJGw/maxresdefault.jpg",
    "movieName": "Milan vs Napoli"
  },

	
	
	
		{
    "bannerCategoryId": "5",
   "fileUrl": "http://185.132.177.110:8080/COSMOTESport3HD/video.m3u8",
    "id": 2,
    "imageUrl": "https://i.ytimg.com/vi/WK4RAbOqG1A/maxresdefault.jpg",
    "movieName": "Bayer Leverkusen vs Arminia Bielefeld"
  },
		{
    "bannerCategoryId": "5",
   "fileUrl": "http://185.132.177.110:8080/COSMOTESport3HD/video.m3u8",
    "id": 2,
    "imageUrl": "https://i.ytimg.com/vi/OMD9ps0cYcQ/maxresdefault.jpg",
    "movieName": "RB Leipzig vs Eintracht Frankfurt"
  },
	{
    "bannerCategoryId": "5",
   "fileUrl": "http://185.132.177.110:8080/COSMOTESport3HD/video.m3u8",
    "id": 2,
    "imageUrl": "https://i.ytimg.com/vi/3HeO7-Rbzmw/hqdefault.jpg",
    "movieName": "Stuttgart vs Hoffenheim"
  }
	
	
	
 
]  
