
[{
		"categoryId": 1,
		"categoryTitle":"CHAMPIONS LEAGUE-------→ ",
		"categoryItemList": [



	
	


			


	{
	"bannerCategoryId": "1",
	
	"fileUrl": "https://www.livedoomovies.com/02_SPORTTV_3_720p/chunklist.m3u8",
         "id": 2,
        "imageUrl": "https://i.ytimg.com/vi/GoPL4_QdP9M/maxresdefault.jpg",
        "movieName": "VILLAREAL VS ARSENAL"
  },
{
	"bannerCategoryId": "1",
	
	"fileUrl": "https://www.livedoomovies.com/02_SPORTTV_2_720p/chunklist.m3u8",
         "id": 2,
        "imageUrl": "https://i.ytimg.com/vi/Ik4-eLAzjHo/maxresdefault.jpg",
        "movieName": "MANCHESTER UNITED VS ROMA"
  }
		
	
  ]
},
		
 {	"categoryId": 2,
		"categoryTitle": " champions league---------------→",
		"categoryItemList": [
	
	
	

	

	{
	"bannerCategoryId": "1",
	
	"fileUrl": "https://www.livedoomovies.com/02_SPORTTV_3_720p/chunklist.m3u8",
         "id": 2,
        "imageUrl": "https://i.ytimg.com/vi/GoPL4_QdP9M/maxresdefault.jpg",
        "movieName": "VILLAREAL VS ARSENAL"
  },
{
	"bannerCategoryId": "1",
	
	"fileUrl": "https://www.livedoomovies.com/02_SPORTTV_2_720p/chunklist.m3u8",
         "id": 2,
        "imageUrl": "https://i.ytimg.com/vi/Ik4-eLAzjHo/maxresdefault.jpg",
        "movieName": "MANCHESTER UNITED VS ROMA"
  }

		]
	}
 ]
